mysql_handler/__init__.py
mysql_handler/connector.py
mysql_handler/query_handler.py
mysql_handler-1.1.1.dist-info/WHEEL
mysql_handler-1.1.1.dist-info/METADATA
mysql_handler-1.1.1.dist-info/RECORD
